{
    "current_condition": [
        {
            "FeelsLikeC": "-2",
            "FeelsLikeF": "28",
            "cloudcover": "75",
            "humidity": "100",
            "localObsDateTime": "2022-02-26 09:01 AM",
            "observation_time": "09:01 AM",
            "precipInches": "0.0",
            "precipMM": "0.0",
            "pressure": "1031",
            "pressureInches": "30",
            "temp_C": "1",
            "temp_F": "34",
            "uvIndex": "2",
            "visibility": "1",
            "visibilityMiles": "0",
            "weatherCode": "248",
            "weatherDesc": [
                {
                    "value": "Fog"
                }
            ],
            "weatherIconUrl": [
                {
                    "value": ""
                }
            ],
            "winddir16Point": "SE",
            "winddirDegree": "140",
            "windspeedKmph": "6",
            "windspeedMiles": "4"
        }
    ],
    "nearest_area": [
        {
            "areaName": [
                {
                    "value": "South View"
                }
            ],
            "country": [
                {
                    "value": "United Kingdom"
                }
            ],
            "latitude": "51.268",
            "longitude": "-1.091",
            "population": "0",
            "region": [
                {
                    "value": "Hampshire"
                }
            ],
            "weatherUrl": [
                {
                    "value": ""
                }
            ]
        }
    ],
    "request": [
        {
            "query": "Lat 51.26 and Lon -1.09",
            "type": "LatLon"
        }
    ],
    "weather": [
        {
            "astronomy": [
                {
                    "moon_illumination": "17",
                    "moon_phase": "Waning Crescent",
                    "moonrise": "04:48 AM",
                    "moonset": "11:56 AM",
                    "sunrise": "06:56 AM",
                    "sunset": "05:40 PM"
                }
            ],
            "avgtempC": "6",
            "avgtempF": "42",
            "date": "2022-02-26",
            "hourly": [
                {
                    "DewPointC": "1",
                    "DewPointF": "34",
                    "FeelsLikeC": "1",
                    "FeelsLikeF": "33",
                    "HeatIndexC": "3",
                    "HeatIndexF": "37",
                    "WindChillC": "1",
                    "WindChillF": "33",
                    "WindGustKmph": "15",
                    "WindGustMiles": "9",
                    "chanceoffog": "0",
                    "chanceoffrost": "0",
                    "chanceofhightemp": "0",
                    "chanceofovercast": "0",
                    "chanceofrain": "0",
                    "chanceofremdry": "92",
                    "chanceofsnow": "0",
                    "chanceofsunshine": "87",
                    "chanceofthunder": "0",
                    "chanceofwindy": "0",
                    "cloudcover": "16",
                    "humidity": "88",
                    "precipInches": "0.0",
                    "precipMM": "0.0",
                    "pressure": "1032",
                    "pressureInches": "30",
                    "tempC": "3",
                    "tempF": "37",
                    "time": "0",
                    "uvIndex": "1",
                    "visibility": "10",
                    "visibilityMiles": "6",
                    "weatherCode": "113",
                    "weatherDesc": [
                        {
                            "value": "Clear"
                        }
                    ],
                    "weatherIconUrl": [
                        {
                            "value": ""
                        }
                    ],
                    "winddir16Point": "SSW",
                    "winddirDegree": "191",
                    "windspeedKmph": "7",
                    "windspeedMiles": "4"
                },
                {
                    "DewPointC": "1",
                    "DewPointF": "33",
                    "FeelsLikeC": "0",
                    "FeelsLikeF": "32",
                    "HeatIndexC": "3",
                    "HeatIndexF": "37",
                    "WindChillC": "0",
                    "WindChillF": "32",
                    "WindGustKmph": "20",
                    "WindGustMiles": "12",
                    "chanceoffog": "0",
                    "chanceoffrost": "0",
                    "chanceofhightemp": "0",
                    "chanceofovercast": "42",
                    "chanceofrain": "0",
                    "chanceofremdry": "84",
                    "chanceofsnow": "0",
                    "chanceofsunshine": "80",
                    "chanceofthunder": "0",
                    "chanceofwindy": "0",
                    "cloudcover": "25",
                    "humidity": "86",
                    "precipInches": "0.0",
                    "precipMM": "0.0",
                    "pressure": "1031",
                    "pressureInches": "30",
                    "tempC": "3",
                    "tempF": "37",
                    "time": "300",
                    "uvIndex": "1",
                    "visibility": "10",
                    "visibilityMiles": "6",
                    "weatherCode": "116",
                    "weatherDesc": [
                        {
                            "value": "Partly cloudy"
                        }
                    ],
                    "weatherIconUrl": [
                        {
                            "value": ""
                        }
                    ],
                    "winddir16Point": "S",
                    "winddirDegree": "183",
                    "windspeedKmph": "9",
                    "windspeedMiles": "6"
                },
                {
                    "DewPointC": "1",
                    "DewPointF": "33",
                    "FeelsLikeC": "-1",
                    "FeelsLikeF": "31",
                    "HeatIndexC": "2",
                    "HeatIndexF": "36",
                    "WindChillC": "-1",
                    "WindChillF": "31",
                    "WindGustKmph": "21",
                    "WindGustMiles": "13",
                    "chanceoffog": "0",
                    "chanceoffrost": "0",
                    "chanceofhightemp": "0",
                    "chanceofovercast": "0",
                    "chanceofrain": "0",
                    "chanceofremdry": "92",
                    "chanceofsnow": "0",
                    "chanceofsunshine": "85",
                    "chanceofthunder": "0",
                    "chanceofwindy": "0",
                    "cloudcover": "4",
                    "humidity": "90",
                    "precipInches": "0.0",
                    "precipMM": "0.0",
                    "pressure": "1030",
                    "pressureInches": "30",
                    "tempC": "2",
                    "tempF": "36",
                    "time": "600",
                    "uvIndex": "1",
                    "visibility": "10",
                    "visibilityMiles": "6",
                    "weatherCode": "113",
                    "weatherDesc": [
                        {
                            "value": "Clear"
                        }
                    ],
                    "weatherIconUrl": [
                        {
                            "value": ""
                        }
                    ],
                    "winddir16Point": "SSE",
                    "winddirDegree": "158",
                    "windspeedKmph": "10",
                    "windspeedMiles": "6"
                },
                {
                    "DewPointC": "4",
                    "DewPointF": "39",
                    "FeelsLikeC": "3",
                    "FeelsLikeF": "38",
                    "HeatIndexC": "7",
                    "HeatIndexF": "44",
                    "WindChillC": "3",
                    "WindChillF": "38",
                    "WindGustKmph": "22",
                    "WindGustMiles": "14",
                    "chanceoffog": "0",
                    "chanceoffrost": "0",
                    "chanceofhightemp": "0",
                    "chanceofovercast": "0",
                    "chanceofrain": "0",
                    "chanceofremdry": "94",
                    "chanceofsnow": "0",
                    "chanceofsunshine": "92",
                    "chanceofthunder": "0",
                    "chanceofwindy": "0",
                    "cloudcover": "10",
                    "humidity": "85",
                    "precipInches": "0.0",
                    "precipMM": "0.0",
                    "pressure": "1030",
                    "pressureInches": "30",
                    "tempC": "7",
                    "tempF": "44",
                    "time": "900",
                    "uvIndex": "3",
                    "visibility": "10",
                    "visibilityMiles": "6",
                    "weatherCode": "113",
                    "weatherDesc": [
                        {
                            "value": "Sunny"
                        }
                    ],
                    "weatherIconUrl": [
                        {
                            "value": ""
                        }
                    ],
                    "winddir16Point": "S",
                    "winddirDegree": "173",
                    "windspeedKmph": "16",
                    "windspeedMiles": "10"
                },
                {
                    "DewPointC": "4",
                    "DewPointF": "38",
                    "FeelsLikeC": "7",
                    "FeelsLikeF": "45",
                    "HeatIndexC": "10",
                    "HeatIndexF": "50",
                    "WindChillC": "7",
                    "WindChillF": "45",
                    "WindGustKmph": "31",
                    "WindGustMiles": "19",
                    "chanceoffog": "0",
                    "chanceoffrost": "0",
                    "chanceofhightemp": "0",
                    "chanceofovercast": "0",
                    "chanceofrain": "0",
                    "chanceofremdry": "87",
                    "chanceofsnow": "0",
                    "chanceofsunshine": "90",
                    "chanceofthunder": "0",
                    "chanceofwindy": "0",
                    "cloudcover": "4",
                    "humidity": "64",
                    "precipInches": "0.0",
                    "precipMM": "0.0",
                    "pressure": "1029",
                    "pressureInches": "30",
                    "tempC": "10",
                    "tempF": "50",
                    "time": "1200",
                    "uvIndex": "4",
                    "visibility": "10",
                    "visibilityMiles": "6",
                    "weatherCode": "113",
                    "weatherDesc": [
                        {
                            "value": "Sunny"
                        }
                    ],
                    "weatherIconUrl": [
                        {
                            "value": ""
                        }
                    ],
                    "winddir16Point": "S",
                    "winddirDegree": "170",
                    "windspeedKmph": "27",
                    "windspeedMiles": "17"
                },
                {
                    "DewPointC": "2",
                    "DewPointF": "36",
                    "FeelsLikeC": "6",
                    "FeelsLikeF": "43",
                    "HeatIndexC": "9",
                    "HeatIndexF": "48",
                    "WindChillC": "6",
                    "WindChillF": "43",
                    "WindGustKmph": "28",
                    "WindGustMiles": "17",
                    "chanceoffog": "0",
                    "chanceoffrost": "0",
                    "chanceofhightemp": "0",
                    "chanceofovercast": "0",
                    "chanceofrain": "0",
                    "chanceofremdry": "84",
                    "chanceofsnow": "0",
                    "chanceofsunshine": "93",
                    "chanceofthunder": "0",
                    "chanceofwindy": "0",
                    "cloudcover": "17",
                    "humidity": "63",
                    "precipInches": "0.0",
                    "precipMM": "0.0",
                    "pressure": "1027",
                    "pressureInches": "30",
                    "tempC": "9",
                    "tempF": "48",
                    "time": "1500",
                    "uvIndex": "3",
                    "visibility": "10",
                    "visibilityMiles": "6",
                    "weatherCode": "113",
                    "weatherDesc": [
                        {
                            "value": "Sunny"
                        }
                    ],
                    "weatherIconUrl": [
                        {
                            "value": ""
                        }
                    ],
                    "winddir16Point": "SSE",
                    "winddirDegree": "159",
                    "windspeedKmph": "24",
                    "windspeedMiles": "15"
                },
                {
                    "DewPointC": "1",
                    "DewPointF": "34",
                    "FeelsLikeC": "2",
                    "FeelsLikeF": "35",
                    "HeatIndexC": "6",
                    "HeatIndexF": "42",
                    "WindChillC": "2",
                    "WindChillF": "35",
                    "WindGustKmph": "30",
                    "WindGustMiles": "18",
                    "chanceoffog": "0",
                    "chanceoffrost": "0",
                    "chanceofhightemp": "0",
                    "chanceofovercast": "93",
                    "chanceofrain": "0",
                    "chanceofremdry": "83",
                    "chanceofsnow": "0",
                    "chanceofsunshine": "10",
                    "chanceofthunder": "0",
                    "chanceofwindy": "0",
                    "cloudcover": "70",
                    "humidity": "72",
                    "precipInches": "0.0",
                    "precipMM": "0.0",
                    "pressure": "1026",
                    "pressureInches": "30",
                    "tempC": "6",
                    "tempF": "42",
                    "time": "1800",
                    "uvIndex": "1",
                    "visibility": "10",
                    "visibilityMiles": "6",
                    "weatherCode": "119",
                    "weatherDesc": [
                        {
                            "value": "Cloudy"
                        }
                    ],
                    "weatherIconUrl": [
                        {
                            "value": ""
                        }
                    ],
                    "winddir16Point": "SE",
                    "winddirDegree": "139",
                    "windspeedKmph": "18",
                    "windspeedMiles": "11"
                },
                {
                    "DewPointC": "0",
                    "DewPointF": "32",
                    "FeelsLikeC": "1",
                    "FeelsLikeF": "33",
                    "HeatIndexC": "5",
                    "HeatIndexF": "40",
                    "WindChillC": "1",
                    "WindChillF": "33",
                    "WindGustKmph": "37",
                    "WindGustMiles": "23",
                    "chanceoffog": "0",
                    "chanceoffrost": "0",
                    "chanceofhightemp": "0",
                    "chanceofovercast": "0",
                    "chanceofrain": "0",
                    "chanceofremdry": "81",
                    "chanceofsnow": "0",
                    "chanceofsunshine": "86",
                    "chanceofthunder": "0",
                    "chanceofwindy": "0",
                    "cloudcover": "11",
                    "humidity": "72",
                    "precipInches": "0.0",
                    "precipMM": "0.0",
                    "pressure": "1025",
                    "pressureInches": "30",
                    "tempC": "5",
                    "tempF": "40",
                    "time": "2100",
                    "uvIndex": "1",
                    "visibility": "10",
                    "visibilityMiles": "6",
                    "weatherCode": "113",
                    "weatherDesc": [
                        {
                            "value": "Clear"
                        }
                    ],
                    "weatherIconUrl": [
                        {
                            "value": ""
                        }
                    ],
                    "winddir16Point": "SE",
                    "winddirDegree": "135",
                    "windspeedKmph": "20",
                    "windspeedMiles": "13"
                }
            ],
            "maxtempC": "10",
            "maxtempF": "49",
            "mintempC": "3",
            "mintempF": "37",
            "sunHour": "10.8",
            "totalSnow_cm": "0.0",
            "uvIndex": "2"
        },
        {
            "astronomy": [
                {
                    "moon_illumination": "9",
                    "moon_phase": "Waning Crescent",
                    "moonrise": "05:44 AM",
                    "moonset": "01:09 PM",
                    "sunrise": "06:54 AM",
                    "sunset": "05:41 PM"
                }
            ],
            "avgtempC": "6",
            "avgtempF": "43",
            "date": "2022-02-27",
            "hourly": [
                {
                    "DewPointC": "-1",
                    "DewPointF": "31",
                    "FeelsLikeC": "-0",
                    "FeelsLikeF": "31",
                    "HeatIndexC": "4",
                    "HeatIndexF": "40",
                    "WindChillC": "-0",
                    "WindChillF": "31",
                    "WindGustKmph": "42",
                    "WindGustMiles": "26",
                    "chanceoffog": "0",
                    "chanceoffrost": "0",
                    "chanceofhightemp": "0",
                    "chanceofovercast": "0",
                    "chanceofrain": "0",
                    "chanceofremdry": "82",
                    "chanceofsnow": "0",
                    "chanceofsunshine": "89",
                    "chanceofthunder": "0",
                    "chanceofwindy": "0",
                    "cloudcover": "5",
                    "humidity": "71",
                    "precipInches": "0.0",
                    "precipMM": "0.0",
                    "pressure": "1024",
                    "pressureInches": "30",
                    "tempC": "4",
                    "tempF": "40",
                    "time": "0",
                    "uvIndex": "1",
                    "visibility": "10",
                    "visibilityMiles": "6",
                    "weatherCode": "113",
                    "weatherDesc": [
                        {
                            "value": "Clear"
                        }
                    ],
                    "weatherIconUrl": [
                        {
                            "value": ""
                        }
                    ],
                    "winddir16Point": "SE",
                    "winddirDegree": "137",
                    "windspeedKmph": "24",
                    "windspeedMiles": "15"
                },
                {
                    "DewPointC": "-1",
                    "DewPointF": "30",
                    "FeelsLikeC": "-1",
                    "FeelsLikeF": "30",
                    "HeatIndexC": "4",
                    "HeatIndexF": "38",
                    "WindChillC": "-1",
                    "WindChillF": "30",
                    "WindGustKmph": "40",
                    "WindGustMiles": "25",
                    "chanceoffog": "0",
                    "chanceoffrost": "0",
                    "chanceofhightemp": "0",
                    "chanceofovercast": "0",
                    "chanceofrain": "0",
                    "chanceofremdry": "87",
                    "chanceofsnow": "0",
                    "chanceofsunshine": "87",
                    "chanceofthunder": "0",
                    "chanceofwindy": "0",
                    "cloudcover": "8",
                    "humidity": "72",
                    "precipInches": "0.0",
                    "precipMM": "0.0",
                    "pressure": "1023",
                    "pressureInches": "30",
                    "tempC": "4",
                    "tempF": "38",
                    "time": "300",
                    "uvIndex": "1",
                    "visibility": "10",
                    "visibilityMiles": "6",
                    "weatherCode": "113",
                    "weatherDesc": [
                        {
                            "value": "Clear"
                        }
                    ],
                    "weatherIconUrl": [
                        {
                            "value": ""
                        }
                    ],
                    "winddir16Point": "SE",
                    "winddirDegree": "141",
                    "windspeedKmph": "23",
                    "windspeedMiles": "14"
                },
                {
                    "DewPointC": "-1",
                    "DewPointF": "30",
                    "FeelsLikeC": "-2",
                    "FeelsLikeF": "29",
                    "HeatIndexC": "3",
                    "HeatIndexF": "37",
                    "WindChillC": "-2",
                    "WindChillF": "29",
                    "WindGustKmph": "36",
                    "WindGustMiles": "22",
                    "chanceoffog": "0",
                    "chanceoffrost": "0",
                    "chanceofhightemp": "0",
                    "chanceofovercast": "0",
                    "chanceofrain": "0",
                    "chanceofremdry": "80",
                    "chanceofsnow": "0",
                    "chanceofsunshine": "85",
                    "chanceofthunder": "0",
                    "chanceofwindy": "0",
                    "cloudcover": "5",
                    "humidity": "76",
                    "precipInches": "0.0",
                    "precipMM": "0.0",
                    "pressure": "1023",
                    "pressureInches": "30",
                    "tempC": "3",
                    "tempF": "37",
                    "time": "600",
                    "uvIndex": "1",
                    "visibility": "10",
                    "visibilityMiles": "6",
                    "weatherCode": "113",
                    "weatherDesc": [
                        {
                            "value": "Clear"
                        }
                    ],
                    "weatherIconUrl": [
                        {
                            "value": ""
                        }
                    ],
                    "winddir16Point": "SE",
                    "winddirDegree": "133",
                    "windspeedKmph": "20",
                    "windspeedMiles": "13"
                },
                {
                    "DewPointC": "-0",
                    "DewPointF": "32",
                    "FeelsLikeC": "0",
                    "FeelsLikeF": "33",
                    "HeatIndexC": "5",
                    "HeatIndexF": "41",
                    "WindChillC": "0",
                    "WindChillF": "33",
                    "WindGustKmph": "36",
                    "WindGustMiles": "23",
                    "chanceoffog": "0",
                    "chanceoffrost": "0",
                    "chanceofhightemp": "0",
                    "chanceofovercast": "0",
                    "chanceofrain": "0",
                    "chanceofremdry": "93",
                    "chanceofsnow": "0",
                    "chanceofsunshine": "89",
                    "chanceofthunder": "0",
                    "chanceofwindy": "0",
                    "cloudcover": "0",
                    "humidity": "69",
                    "precipInches": "0.0",
                    "precipMM": "0.0",
                    "pressure": "1023",
                    "pressureInches": "30",
                    "tempC": "5",
                    "tempF": "41",
                    "time": "900",
                    "uvIndex": "3",
                    "visibility": "10",
                    "visibilityMiles": "6",
                    "weatherCode": "113",
                    "weatherDesc": [
                        {
                            "value": "Sunny"
                        }
                    ],
                    "weatherIconUrl": [
                        {
                            "value": ""
                        }
                    ],
                    "winddir16Point": "SE",
                    "winddirDegree": "136",
                    "windspeedKmph": "27",
                    "windspeedMiles": "17"
                },
                {
                    "DewPointC": "2",
                    "DewPointF": "36",
                    "FeelsLikeC": "7",
                    "FeelsLikeF": "45",
                    "HeatIndexC": "10",
                    "HeatIndexF": "51",
                    "WindChillC": "7",
                    "WindChillF": "45",
                    "WindGustKmph": "35",
                    "WindGustMiles": "22",
                    "chanceoffog": "0",
                    "chanceoffrost": "0",
                    "chanceofhightemp": "0",
                    "chanceofovercast": "0",
                    "chanceofrain": "0",
                    "chanceofremdry": "84",
                    "chanceofsnow": "0",
                    "chanceofsunshine": "94",
                    "chanceofthunder": "0",
                    "chanceofwindy": "0",
                    "cloudcover": "0",
                    "humidity": "56",
                    "precipInches": "0.0",
                    "precipMM": "0.0",
                    "pressure": "1022",
                    "pressureInches": "30",
                    "tempC": "10",
                    "tempF": "51",
                    "time": "1200",
                    "uvIndex": "4",
                    "visibility": "10",
                    "visibilityMiles": "6",
                    "weatherCode": "113",
                    "weatherDesc": [
                        {
                            "value": "Sunny"
                        }
                    ],
                    "weatherIconUrl": [
                        {
                            "value": ""
                        }
                    ],
                    "winddir16Point": "SSE",
                    "winddirDegree": "149",
                    "windspeedKmph": "30",
                    "windspeedMiles": "19"
                },
                {
                    "DewPointC": "3",
                    "DewPointF": "38",
                    "FeelsLikeC": "8",
                    "FeelsLikeF": "46",
                    "HeatIndexC": "11",
                    "HeatIndexF": "51",
                    "WindChillC": "8",
                    "WindChillF": "46",
                    "WindGustKmph": "30",
                    "WindGustMiles": "19",
                    "chanceoffog": "0",
                    "chanceoffrost": "0",
                    "chanceofhightemp": "0",
                    "chanceofovercast": "0",
                    "chanceofrain": "0",
                    "chanceofremdry": "81",
                    "chanceofsnow": "0",
                    "chanceofsunshine": "86",
                    "chanceofthunder": "0",
                    "chanceofwindy": "0",
                    "cloudcover": "0",
                    "humidity": "60",
                    "precipInches": "0.0",
                    "precipMM": "0.0",
                    "pressure": "1022",
                    "pressureInches": "30",
                    "tempC": "11",
                    "tempF": "51",
                    "time": "1500",
                    "uvIndex": "4",
                    "visibility": "10",
                    "visibilityMiles": "6",
                    "weatherCode": "113",
                    "weatherDesc": [
                        {
                            "value": "Sunny"
                        }
                    ],
                    "weatherIconUrl": [
                        {
                            "value": ""
                        }
                    ],
                    "winddir16Point": "SSE",
                    "winddirDegree": "149",
                    "windspeedKmph": "26",
                    "windspeedMiles": "16"
                },
                {
                    "DewPointC": "3",
                    "DewPointF": "37",
                    "FeelsLikeC": "5",
                    "FeelsLikeF": "40",
                    "HeatIndexC": "8",
                    "HeatIndexF": "46",
                    "WindChillC": "5",
                    "WindChillF": "40",
                    "WindGustKmph": "20",
                    "WindGustMiles": "13",
                    "chanceoffog": "0",
                    "chanceoffrost": "0",
                    "chanceofhightemp": "0",
                    "chanceofovercast": "0",
                    "chanceofrain": "0",
                    "chanceofremdry": "86",
                    "chanceofsnow": "0",
                    "chanceofsunshine": "88",
                    "chanceofthunder": "0",
                    "chanceofwindy": "0",
                    "cloudcover": "3",
                    "humidity": "72",
                    "precipInches": "0.0",
                    "precipMM": "0.0",
                    "pressure": "1022",
                    "pressureInches": "30",
                    "tempC": "8",
                    "tempF": "46",
                    "time": "1800",
                    "uvIndex": "1",
                    "visibility": "10",
                    "visibilityMiles": "6",
                    "weatherCode": "113",
                    "weatherDesc": [
                        {
                            "value": "Clear"
                        }
                    ],
                    "weatherIconUrl": [
                        {
                            "value": ""
                        }
                    ],
                    "winddir16Point": "SSE",
                    "winddirDegree": "148",
                    "windspeedKmph": "18",
                    "windspeedMiles": "11"
                },
                {
                    "DewPointC": "2",
                    "DewPointF": "36",
                    "FeelsLikeC": "1",
                    "FeelsLikeF": "34",
                    "HeatIndexC": "5",
                    "HeatIndexF": "41",
                    "WindChillC": "1",
                    "WindChillF": "34",
                    "WindGustKmph": "36",
                    "WindGustMiles": "22",
                    "chanceoffog": "0",
                    "chanceoffrost": "0",
                    "chanceofhightemp": "0",
                    "chanceofovercast": "42",
                    "chanceofrain": "0",
                    "chanceofremdry": "81",
                    "chanceofsnow": "0",
                    "chanceofsunshine": "70",
                    "chanceofthunder": "0",
                    "chanceofwindy": "0",
                    "cloudcover": "33",
                    "humidity": "80",
                    "precipInches": "0.0",
                    "precipMM": "0.0",
                    "pressure": "1022",
                    "pressureInches": "30",
                    "tempC": "5",
                    "tempF": "41",
                    "time": "2100",
                    "uvIndex": "1",
                    "visibility": "10",
                    "visibilityMiles": "6",
                    "weatherCode": "116",
                    "weatherDesc": [
                        {
                            "value": "Partly cloudy"
                        }
                    ],
                    "weatherIconUrl": [
                        {
                            "value": ""
                        }
                    ],
                    "winddir16Point": "SSE",
                    "winddirDegree": "153",
                    "windspeedKmph": "19",
                    "windspeedMiles": "12"
                }
            ],
            "maxtempC": "11",
            "maxtempF": "51",
            "mintempC": "3",
            "mintempF": "37",
            "sunHour": "10.9",
            "totalSnow_cm": "0.0",
            "uvIndex": "2"
        },
        {
            "astronomy": [
                {
                    "moon_illumination": "2",
                    "moon_phase": "Waning Crescent",
                    "moonrise": "06:25 AM",
                    "moonset": "02:33 PM",
                    "sunrise": "06:51 AM",
                    "sunset": "05:43 PM"
                }
            ],
            "avgtempC": "8",
            "avgtempF": "47",
            "date": "2022-02-28",
            "hourly": [
                {
                    "DewPointC": "5",
                    "DewPointF": "41",
                    "FeelsLikeC": "5",
                    "FeelsLikeF": "40",
                    "HeatIndexC": "8",
                    "HeatIndexF": "46",
                    "WindChillC": "5",
                    "WindChillF": "40",
                    "WindGustKmph": "30",
                    "WindGustMiles": "19",
                    "chanceoffog": "0",
                    "chanceoffrost": "0",
                    "chanceofhightemp": "0",
                    "chanceofovercast": "94",
                    "chanceofrain": "0",
                    "chanceofremdry": "91",
                    "chanceofsnow": "0",
                    "chanceofsunshine": "7",
                    "chanceofthunder": "0",
                    "chanceofwindy": "0",
                    "cloudcover": "100",
                    "humidity": "85",
                    "precipInches": "0.0",
                    "precipMM": "0.0",
                    "pressure": "1022",
                    "pressureInches": "30",
                    "tempC": "8",
                    "tempF": "46",
                    "time": "0",
                    "uvIndex": "1",
                    "visibility": "10",
                    "visibilityMiles": "6",
                    "weatherCode": "122",
                    "weatherDesc": [
                        {
                            "value": "Overcast"
                        }
                    ],
                    "weatherIconUrl": [
                        {
                            "value": ""
                        }
                    ],
                    "winddir16Point": "SSE",
                    "winddirDegree": "169",
                    "windspeedKmph": "19",
                    "windspeedMiles": "12"
                },
                {
                    "DewPointC": "6",
                    "DewPointF": "43",
                    "FeelsLikeC": "4",
                    "FeelsLikeF": "39",
                    "HeatIndexC": "7",
                    "HeatIndexF": "44",
                    "WindChillC": "4",
                    "WindChillF": "39",
                    "WindGustKmph": "26",
                    "WindGustMiles": "16",
                    "chanceoffog": "0",
                    "chanceoffrost": "0",
                    "chanceofhightemp": "0",
                    "chanceofovercast": "85",
                    "chanceofrain": "0",
                    "chanceofremdry": "83",
                    "chanceofsnow": "0",
                    "chanceofsunshine": "13",
                    "chanceofthunder": "0",
                    "chanceofwindy": "0",
                    "cloudcover": "100",
                    "humidity": "95",
                    "precipInches": "0.0",
                    "precipMM": "0.0",
                    "pressure": "1022",
                    "pressureInches": "30",
                    "tempC": "7",
                    "tempF": "44",
                    "time": "300",
                    "uvIndex": "1",
                    "visibility": "10",
                    "visibilityMiles": "6",
                    "weatherCode": "122",
                    "weatherDesc": [
                        {
                            "value": "Overcast"
                        }
                    ],
                    "weatherIconUrl": [
                        {
                            "value": ""
                        }
                    ],
                    "winddir16Point": "S",
                    "winddirDegree": "171",
                    "windspeedKmph": "16",
                    "windspeedMiles": "10"
                },
                {
                    "DewPointC": "7",
                    "DewPointF": "45",
                    "FeelsLikeC": "5",
                    "FeelsLikeF": "41",
                    "HeatIndexC": "8",
                    "HeatIndexF": "46",
                    "WindChillC": "5",
                    "WindChillF": "41",
                    "WindGustKmph": "25",
                    "WindGustMiles": "16",
                    "chanceoffog": "6",
                    "chanceoffrost": "0",
                    "chanceofhightemp": "0",
                    "chanceofovercast": "81",
                    "chanceofrain": "0",
                    "chanceofremdry": "80",
                    "chanceofsnow": "0",
                    "chanceofsunshine": "9",
                    "chanceofthunder": "0",
                    "chanceofwindy": "0",
                    "cloudcover": "100",
                    "humidity": "97",
                    "precipInches": "0.0",
                    "precipMM": "0.0",
                    "pressure": "1022",
                    "pressureInches": "30",
                    "tempC": "8",
                    "tempF": "46",
                    "time": "600",
                    "uvIndex": "1",
                    "visibility": "10",
                    "visibilityMiles": "6",
                    "weatherCode": "122",
                    "weatherDesc": [
                        {
                            "value": "Overcast"
                        }
                    ],
                    "weatherIconUrl": [
                        {
                            "value": ""
                        }
                    ],
                    "winddir16Point": "S",
                    "winddirDegree": "181",
                    "windspeedKmph": "16",
                    "windspeedMiles": "10"
                },
                {
                    "DewPointC": "7",
                    "DewPointF": "44",
                    "FeelsLikeC": "5",
                    "FeelsLikeF": "41",
                    "HeatIndexC": "8",
                    "HeatIndexF": "47",
                    "WindChillC": "5",
                    "WindChillF": "41",
                    "WindGustKmph": "27",
                    "WindGustMiles": "17",
                    "chanceoffog": "0",
                    "chanceoffrost": "0",
                    "chanceofhightemp": "0",
                    "chanceofovercast": "88",
                    "chanceofrain": "0",
                    "chanceofremdry": "80",
                    "chanceofsnow": "0",
                    "chanceofsunshine": "11",
                    "chanceofthunder": "0",
                    "chanceofwindy": "0",
                    "cloudcover": "77",
                    "humidity": "91",
                    "precipInches": "0.0",
                    "precipMM": "0.0",
                    "pressure": "1022",
                    "pressureInches": "30",
                    "tempC": "8",
                    "tempF": "47",
                    "time": "900",
                    "uvIndex": "2",
                    "visibility": "10",
                    "visibilityMiles": "6",
                    "weatherCode": "119",
                    "weatherDesc": [
                        {
                            "value": "Cloudy"
                        }
                    ],
                    "weatherIconUrl": [
                        {
                            "value": ""
                        }
                    ],
                    "winddir16Point": "S",
                    "winddirDegree": "177",
                    "windspeedKmph": "18",
                    "windspeedMiles": "11"
                },
                {
                    "DewPointC": "7",
                    "DewPointF": "45",
                    "FeelsLikeC": "7",
                    "FeelsLikeF": "44",
                    "HeatIndexC": "10",
                    "HeatIndexF": "49",
                    "WindChillC": "7",
                    "WindChillF": "44",
                    "WindGustKmph": "28",
                    "WindGustMiles": "18",
                    "chanceoffog": "0",
                    "chanceoffrost": "0",
                    "chanceofhightemp": "0",
                    "chanceofovercast": "81",
                    "chanceofrain": "0",
                    "chanceofremdry": "92",
                    "chanceofsnow": "0",
                    "chanceofsunshine": "14",
                    "chanceofthunder": "0",
                    "chanceofwindy": "0",
                    "cloudcover": "79",
                    "humidity": "84",
                    "precipInches": "0.0",
                    "precipMM": "0.0",
                    "pressure": "1022",
                    "pressureInches": "30",
                    "tempC": "10",
                    "tempF": "49",
                    "time": "1200",
                    "uvIndex": "2",
                    "visibility": "10",
                    "visibilityMiles": "6",
                    "weatherCode": "119",
                    "weatherDesc": [
                        {
                            "value": "Cloudy"
                        }
                    ],
                    "weatherIconUrl": [
                        {
                            "value": ""
                        }
                    ],
                    "winddir16Point": "SSW",
                    "winddirDegree": "192",
                    "windspeedKmph": "22",
                    "windspeedMiles": "14"
                },
                {
                    "DewPointC": "8",
                    "DewPointF": "46",
                    "FeelsLikeC": "6",
                    "FeelsLikeF": "43",
                    "HeatIndexC": "9",
                    "HeatIndexF": "48",
                    "WindChillC": "6",
                    "WindChillF": "43",
                    "WindGustKmph": "32",
                    "WindGustMiles": "20",
                    "chanceoffog": "0",
                    "chanceoffrost": "0",
                    "chanceofhightemp": "0",
                    "chanceofovercast": "80",
                    "chanceofrain": "76",
                    "chanceofremdry": "0",
                    "chanceofsnow": "0",
                    "chanceofsunshine": "0",
                    "chanceofthunder": "0",
                    "chanceofwindy": "0",
                    "cloudcover": "100",
                    "humidity": "92",
                    "precipInches": "0.0",
                    "precipMM": "0.6",
                    "pressure": "1021",
                    "pressureInches": "30",
                    "tempC": "9",
                    "tempF": "48",
                    "time": "1500",
                    "uvIndex": "2",
                    "visibility": "2",
                    "visibilityMiles": "1",
                    "weatherCode": "266",
                    "weatherDesc": [
                        {
                            "value": "Light drizzle"
                        }
                    ],
                    "weatherIconUrl": [
                        {
                            "value": ""
                        }
                    ],
                    "winddir16Point": "S",
                    "winddirDegree": "188",
                    "windspeedKmph": "24",
                    "windspeedMiles": "15"
                },
                {
                    "DewPointC": "9",
                    "DewPointF": "48",
                    "FeelsLikeC": "7",
                    "FeelsLikeF": "44",
                    "HeatIndexC": "10",
                    "HeatIndexF": "49",
                    "WindChillC": "7",
                    "WindChillF": "44",
                    "WindGustKmph": "30",
                    "WindGustMiles": "19",
                    "chanceoffog": "0",
                    "chanceoffrost": "0",
                    "chanceofhightemp": "0",
                    "chanceofovercast": "88",
                    "chanceofrain": "75",
                    "chanceofremdry": "0",
                    "chanceofsnow": "0",
                    "chanceofsunshine": "0",
                    "chanceofthunder": "0",
                    "chanceofwindy": "0",
                    "cloudcover": "100",
                    "humidity": "97",
                    "precipInches": "0.0",
                    "precipMM": "1.0",
                    "pressure": "1020",
                    "pressureInches": "30",
                    "tempC": "10",
                    "tempF": "49",
                    "time": "1800",
                    "uvIndex": "1",
                    "visibility": "9",
                    "visibilityMiles": "5",
                    "weatherCode": "296",
                    "weatherDesc": [
                        {
                            "value": "Light rain"
                        }
                    ],
                    "weatherIconUrl": [
                        {
                            "value": ""
                        }
                    ],
                    "winddir16Point": "SSW",
                    "winddirDegree": "191",
                    "windspeedKmph": "22",
                    "windspeedMiles": "14"
                },
                {
                    "DewPointC": "7",
                    "DewPointF": "44",
                    "FeelsLikeC": "5",
                    "FeelsLikeF": "40",
                    "HeatIndexC": "8",
                    "HeatIndexF": "47",
                    "WindChillC": "5",
                    "WindChillF": "40",
                    "WindGustKmph": "33",
                    "WindGustMiles": "21",
                    "chanceoffog": "0",
                    "chanceoffrost": "0",
                    "chanceofhightemp": "0",
                    "chanceofovercast": "86",
                    "chanceofrain": "68",
                    "chanceofremdry": "0",
                    "chanceofsnow": "0",
                    "chanceofsunshine": "0",
                    "chanceofthunder": "0",
                    "chanceofwindy": "0",
                    "cloudcover": "100",
                    "humidity": "92",
                    "precipInches": "0.1",
                    "precipMM": "2.4",
                    "pressure": "1023",
                    "pressureInches": "30",
                    "tempC": "8",
                    "tempF": "47",
                    "time": "2100",
                    "uvIndex": "1",
                    "visibility": "9",
                    "visibilityMiles": "5",
                    "weatherCode": "296",
                    "weatherDesc": [
                        {
                            "value": "Light rain"
                        }
                    ],
                    "weatherIconUrl": [
                        {
                            "value": ""
                        }
                    ],
                    "winddir16Point": "NW",
                    "winddirDegree": "319",
                    "windspeedKmph": "25",
                    "windspeedMiles": "15"
                }
            ],
            "maxtempC": "11",
            "maxtempF": "51",
            "mintempC": "5",
            "mintempF": "41",
            "sunHour": "8.3",
            "totalSnow_cm": "0.0",
            "uvIndex": "1"
        }
    ]
}